{
  "centres": [
    {
      "centre_id": "aberdeen_north",
      "centre_name": "Aberdeen North",
      "lat": 57.1855304,
      "lng": -2.0962169
    },
    {
      "centre_id": "aberfeldy",
      "centre_name": "Aberfeldy",
      "lat": 56.6193213,
      "lng": -3.86509
    },
    {
      "centre_id": "abergavenny",
      "centre_name": "Abergavenny",
      "lat": 51.8159651,
      "lng": -3.0106159
    },
    {
      "centre_id": "aberystwyth_park_avenue",
      "centre_name": "Aberystwyth Park Avenue",
      "lat": 52.4104912,
      "lng": -4.0809466
    },
    {
      "centre_id": "airdrie",
      "centre_name": "Airdrie",
      "lat": 55.8661181,
      "lng": -3.9804785
    },
    {
      "centre_id": "alness",
      "centre_name": "Alness",
      "lat": 57.6906806,
      "lng": -4.2679679
    },
    {
      "centre_id": "alnwick",
      "centre_name": "Alnwick",
      "lat": 55.4133398,
      "lng": -1.7072354
    },
    {
      "centre_id": "arbroath",
      "centre_name": "Arbroath",
      "lat": 56.5586729,
      "lng": -2.5815669
    },
    {
      "centre_id": "ashfield",
      "centre_name": "Ashfield",
      "lat": 53.0897738,
      "lng": -1.2518767
    },
    {
      "centre_id": "ashford_kent",
      "centre_name": "Ashford Kent",
      "lat": 51.1401671,
      "lng": 0.8436134
    },
    {
      "centre_id": "ashford_london_middlesex",
      "centre_name": "Ashford London Middlesex",
      "lat": null,
      "lng": null
    },
    {
      "centre_id": "aylesbury",
      "centre_name": "Aylesbury",
      "lat": 51.8161412,
      "lng": -0.8130383
    },
    {
      "centre_id": "ayr",
      "centre_name": "Ayr",
      "lat": 55.4628044,
      "lng": -4.6302502
    },
    {
      "centre_id": "bala",
      "centre_name": "Bala",
      "lat": 52.9112205,
      "lng": -3.59947
    },
    {
      "centre_id": "ballater",
      "centre_name": "Ballater",
      "lat": 57.0495064,
      "lng": -3.0405173
    },
    {
      "centre_id": "banbury",
      "centre_name": "Banbury",
      "lat": 52.0552294,
      "lng": -1.3499525
    },
    {
      "centre_id": "banff",
      "centre_name": "Banff",
      "lat": 57.6645459,
      "lng": -2.5217539
    },
    {
      "centre_id": "bangor",
      "centre_name": "Bangor",
      "lat": 38.0266291,
      "lng": -84.5047222
    },
    {
      "centre_id": "barking_tanner_street",
      "centre_name": "Barking Tanner Street",
      "lat": 51.5434527,
      "lng": 0.0779592
    },
    {
      "centre_id": "barnet_london",
      "centre_name": "Barnet London",
      "lat": 51.6127446,
      "lng": -0.211689
    },
    {
      "centre_id": "barnsley",
      "centre_name": "Barnsley",
      "lat": 53.5527719,
      "lng": -1.4827755
    },
    {
      "centre_id": "barnstaple",
      "centre_name": "Barnstaple",
      "lat": 51.0804057,
      "lng": -4.0600467
    },
    {
      "centre_id": "barra",
      "centre_name": "Barra",
      "lat": 57.0017747,
      "lng": -7.4696854
    },
    {
      "centre_id": "barrow_in_furness",
      "centre_name": "Barrow In Furness",
      "lat": 54.1194266,
      "lng": -3.2426945
    },
    {
      "centre_id": "barry",
      "centre_name": "Barry",
      "lat": 51.4065052,
      "lng": -3.2666925
    },
    {
      "centre_id": "basingstoke",
      "centre_name": "Basingstoke",
      "lat": 51.2452589,
      "lng": -1.1124597
    },
    {
      "centre_id": "bedford",
      "centre_name": "Bedford",
      "lat": 52.1363806,
      "lng": -0.4675041
    },
    {
      "centre_id": "belvedere_london",
      "centre_name": "Belvedere London",
      "lat": 51.483662,
      "lng": 0.1431363
    },
    {
      "centre_id": "berwick_on_tweed",
      "centre_name": "Berwick-On-Tweed",
      "lat": 55.7692442,
      "lng": -2.0026472
    },
    {
      "centre_id": "birmingham_garretts_green",
      "centre_name": "Birmingham Garretts Green",
      "lat": 52.4734898,
      "lng": -1.7799814
    },
    {
      "centre_id": "birmingham_kings_heath",
      "centre_name": "Birmingham Kings Heath",
      "lat": 52.4350754,
      "lng": -1.8929234
    },
    {
      "centre_id": "birmingham_kingstanding",
      "centre_name": "Birmingham Kingstanding",
      "lat": 52.5441569,
      "lng": -1.8905068
    },
    {
      "centre_id": "birmingham_shirley",
      "centre_name": "Birmingham Shirley",
      "lat": 52.4164368,
      "lng": -1.8303545
    },
    {
      "centre_id": "birmingham_south_yardley",
      "centre_name": "Birmingham South Yardley",
      "lat": 52.4551082,
      "lng": -1.8103696
    },
    {
      "centre_id": "birmingham_sutton_coldfield",
      "centre_name": "Birmingham Sutton Coldfield",
      "lat": 52.5269034,
      "lng": -1.7890739
    },
    {
      "centre_id": "bishops_stortford",
      "centre_name": "Bishops Stortford",
      "lat": 51.8773423,
      "lng": 0.1511094
    },
    {
      "centre_id": "blackburn_with_darwen",
      "centre_name": "Blackburn with Darwen",
      "lat": 53.7512656,
      "lng": -2.4798825
    },
    {
      "centre_id": "blackpool",
      "centre_name": "Blackpool",
      "lat": 53.8179442,
      "lng": -3.0509812
    },
    {
      "centre_id": "bletchley",
      "centre_name": "Bletchley",
      "lat": 51.9943694,
      "lng": -0.7325655
    },
    {
      "centre_id": "blyth",
      "centre_name": "Blyth",
      "lat": 55.1270903,
      "lng": -1.5099726
    },
    {
      "centre_id": "bodmin",
      "centre_name": "Bodmin",
      "lat": 50.46445,
      "lng": -4.71458
    },
    {
      "centre_id": "bolton_manchester",
      "centre_name": "Bolton Manchester",
      "lat": 53.5643729,
      "lng": -2.4575925
    },
    {
      "centre_id": "borehamwood_london",
      "centre_name": "Borehamwood London",
      "lat": null,
      "lng": null
    },
    {
      "centre_id": "boston",
      "centre_name": "Boston",
      "lat": 52.9748791,
      "lng": -0.0230679
    },
    {
      "centre_id": "bradford_heaton",
      "centre_name": "Bradford Heaton",
      "lat": 53.8173694,
      "lng": -1.7763607
    },
    {
      "centre_id": "bradford_thornbury",
      "centre_name": "Bradford Thornbury",
      "lat": 53.800736,
      "lng": -1.7125246
    },
    {
      "centre_id": "brecon",
      "centre_name": "Brecon",
      "lat": 51.9464734,
      "lng": -3.384174
    },
    {
      "centre_id": "bredbury_manchester",
      "centre_name": "Bredbury Manchester",
      "lat": 53.4230377,
      "lng": -2.1104918
    },
    {
      "centre_id": "brentwood_london",
      "centre_name": "Brentwood London",
      "lat": 51.596265,
      "lng": 0.2570322
    },
    {
      "centre_id": "bridgend",
      "centre_name": "Bridgend",
      "lat": 51.5049859,
      "lng": -3.5756674
    },
    {
      "centre_id": "bridlington",
      "centre_name": "Bridlington",
      "lat": 54.0765756,
      "lng": -0.2000212
    },
    {
      "centre_id": "bristol_brislington",
      "centre_name": "Bristol Brislington",
      "lat": 51.4272861,
      "lng": -2.5608861
    },
    {
      "centre_id": "brodick_isle_of_arran",
      "centre_name": "Brodick Isle of Arran",
      "lat": 55.5939276,
      "lng": -5.1507477
    },
    {
      "centre_id": "buckie",
      "centre_name": "Buckie",
      "lat": 57.6763316,
      "lng": -2.9648866
    },
    {
      "centre_id": "burgess_hill",
      "centre_name": "Burgess Hill",
      "lat": 50.9525936,
      "lng": -0.1531622
    },
    {
      "centre_id": "burton_on_trent",
      "centre_name": "Burton on Trent",
      "lat": 52.8027644,
      "lng": -1.6299047
    },
    {
      "centre_id": "bury_manchester",
      "centre_name": "Bury Manchester",
      "lat": 53.5932971,
      "lng": -2.2981959
    },
    {
      "centre_id": "bury_st_edmunds",
      "centre_name": "Bury St Edmunds",
      "lat": 52.2460367,
      "lng": 0.7125173
    },
    {
      "centre_id": "buxton",
      "centre_name": "Buxton",
      "lat": 53.2589368,
      "lng": -1.9128341
    },
    {
      "centre_id": "camborne",
      "centre_name": "Camborne",
      "lat": 50.2138828,
      "lng": -5.2990347
    },
    {
      "centre_id": "campbeltown",
      "centre_name": "Campbeltown",
      "lat": 55.4242376,
      "lng": -5.6052078
    },
    {
      "centre_id": "canterbury",
      "centre_name": "Canterbury",
      "lat": 51.2800275,
      "lng": 1.0802533
    },
    {
      "centre_id": "cardiff_llanishen",
      "centre_name": "Cardiff Llanishen",
      "lat": 51.5228307,
      "lng": -3.192322
    },
    {
      "centre_id": "cardigan",
      "centre_name": "Cardigan",
      "lat": 52.0839973,
      "lng": -4.6604224
    },
    {
      "centre_id": "carlisle",
      "centre_name": "Carlisle",
      "lat": 54.8744672,
      "lng": -2.8982541
    },
    {
      "centre_id": "carmarthen",
      "centre_name": "Carmarthen",
      "lat": 51.8591257,
      "lng": -4.3115907
    },
    {
      "centre_id": "castle_douglas",
      "centre_name": "Castle Douglas",
      "lat": 54.9390982,
      "lng": -3.9320191
    },
    {
      "centre_id": "cheetham_hill_manchester",
      "centre_name": "Cheetham Hill Manchester",
      "lat": 53.4930022,
      "lng": -2.2516024
    },
    {
      "centre_id": "chelmsford",
      "centre_name": "Chelmsford",
      "lat": 51.7227234,
      "lng": 0.4484230196012416
      },
    {
      "centre_id": "cheltenham",
      "centre_name": "Cheltenham",
      "lat": 51.9241557,
      "lng": -2.0932664
    },
    {
      "centre_id": "chertsey_london",
      "centre_name": "Chertsey London",
      "lat": 51.384675,
      "lng": -0.4920323
    },
    {
      "centre_id": "chester",
      "centre_name": "Chester",
      "lat": 51.87249038,
      "lng": 0.928845203
    },
    {
      "centre_id": "chesterfield",
      "centre_name": "Chesterfield",
      "lat": 53.2352134,
      "lng": -1.4264097
    },
    {
      "centre_id": "chichester",
      "centre_name": "Chichester",
      "lat": 50.8364862,
      "lng": -0.7791721
    },
    {
      "centre_id": "chingford_london",
      "centre_name": "Chingford London",
      "lat": 51.6188236,
      "lng": 0.0039968
    },
    {
      "centre_id": "chippenham",
      "centre_name": "Chippenham",
      "lat": 51.4462746,
      "lng": -2.1484355
    },
    {
      "centre_id": "chorley",
      "centre_name": "Chorley",
      "lat": 53.6575267,
      "lng": -2.6185602
    },
    {
      "centre_id": "clacton_on_sea",
      "centre_name": "Clacton-on-Sea",
      "lat": 51.7895,
      "lng": 1.1512
    },
    {
      "centre_id": "colchester",
      "centre_name": "Colchester",
      "lat": 51.872116,
      "lng": 0.928174
    },
    {
      "centre_id": "coventry",
      "centre_name": "Coventry",
      "lat": 52.4636278,
      "lng": -1.4758167
    },
    {
      "centre_id": "crawley",
      "centre_name": "Crawley",
      "lat": 51.0809358,
      "lng": -0.2017537
    },
    {
      "centre_id": "crewe",
      "centre_name": "Crewe",
      "lat": 53.0977225,
      "lng": -2.4652041
    },
    {
      "centre_id": "crieff",
      "centre_name": "Crieff",
      "lat": 56.372717,
      "lng": -3.8397453
    },
    {
      "centre_id": "croydon_london",
      "centre_name": "Croydon London",
      "lat": 51.3684757,
      "lng": -0.1055694
    },
    {
      "centre_id": "cumnock",
      "centre_name": "Cumnock",
      "lat": 55.4667518,
      "lng": -4.2958473
    },
    {
      "centre_id": "darlington",
      "centre_name": "Darlington",
      "lat": 54.5163618,
      "lng": -1.5094095
    },
    {
      "centre_id": "derby_alvaston",
      "centre_name": "Derby Alvaston",
      "lat": 52.896464,
      "lng": -1.4276734
    },
    {
      "centre_id": "doncaster",
      "centre_name": "Doncaster",
      "lat": 53.5227681,
      "lng": -1.1335312
    },
    {
      "centre_id": "dorchester",
      "centre_name": "Dorchester",
      "lat": 50.7132064,
      "lng": -2.4371229
    },
    {
      "centre_id": "dumbarton",
      "centre_name": "Dumbarton",
      "lat": 55.9432443,
      "lng": -4.5708479
    },
    {
      "centre_id": "dumfries",
      "centre_name": "Dumfries",
      "lat": 55.0691959,
      "lng": -3.6108706
    },
    {
      "centre_id": "dundee",
      "centre_name": "Dundee",
      "lat": 56.4605938,
      "lng": -2.97019
    },
    {
      "centre_id": "dunfermline_vine",
      "centre_name": "Dunfermline Vine",
      "lat": 56.0757041,
      "lng": -3.4261335
    },
    {
      "centre_id": "dunoon",
      "centre_name": "Dunoon",
      "lat": 55.9477081,
      "lng": -4.9235135
    },
    {
      "centre_id": "duns",
      "centre_name": "Duns",
      "lat": 55.777842,
      "lng": -2.3438476
    },
    {
      "centre_id": "durham",
      "centre_name": "Durham",
      "lat": 54.7662651,
      "lng": -1.5461603
    },
    {
      "centre_id": "eastbourne",
      "centre_name": "Eastbourne",
      "lat": 50.7824931,
      "lng": 0.3096792
    },
    {
      "centre_id": "edinburgh_currie",
      "centre_name": "Edinburgh Currie",
      "lat": 55.8999009,
      "lng": -3.3078134
    },
    {
      "centre_id": "elgin",
      "centre_name": "Elgin",
      "lat": 57.6487891,
      "lng": -3.3148459
    },
    {
      "centre_id": "elswick",
      "centre_name": "Elswick",
      "lat": 54.9646227,
      "lng": -1.6565155
    },
    {
      "centre_id": "enfield_innova_business_park",
      "centre_name": "Enfield Innova Business Park",
      "lat": null,
      "lng": null
    },
    {
      "centre_id": "exeter",
      "centre_name": "Exeter",
      "lat": 50.7560635,
      "lng": -3.435726
    },
    {
      "centre_id": "farnborough",
      "centre_name": "Farnborough",
      "lat": 51.2918693,
      "lng": -0.7539836
    },
    {
      "centre_id": "folkestone",
      "centre_name": "Folkestone",
      "lat": 51.0796276,
      "lng": 1.1706318
    },
    {
      "centre_id": "forfar",
      "centre_name": "Forfar",
      "lat": 56.6443013,
      "lng": -2.888212
    },
    {
      "centre_id": "fort_william",
      "centre_name": "Fort William",
      "lat": 56.8178257,
      "lng": -5.1109516
    },
    {
      "centre_id": "fraserburgh",
      "centre_name": "Fraserburgh",
      "lat": 57.689357,
      "lng": -2.0243879
    },
    {
      "centre_id": "gairloch",
      "centre_name": "Gairloch",
      "lat": 57.7280125,
      "lng": -5.6903434
    },
    {
      "centre_id": "galashiels",
      "centre_name": "Galashiels",
      "lat": 55.6156505,
      "lng": -2.8061618
    },
    {
      "centre_id": "gateshead",
      "centre_name": "Gateshead",
      "lat": 54.9221701,
      "lng": -1.590615
    },
    {
      "centre_id": "gillingham",
      "centre_name": "Gillingham",
      "lat": 51.3408551,
      "lng": 0.5706932
    },
    {
      "centre_id": "glasgow_shieldhall",
      "centre_name": "Glasgow Shieldhall",
      "lat": 55.8641479,
      "lng": -4.34911
    },
    {
      "centre_id": "gloucester",
      "centre_name": "Gloucester",
      "lat": 51.8306224,
      "lng": -2.2633028
    },
    {
      "centre_id": "goodmayes_london",
      "centre_name": "Goodmayes London",
      "lat": 51.565803,
      "lng": 0.1119305
    },
    {
      "centre_id": "grantham_somerby",
      "centre_name": "Grantham Somerby",
      "lat": 52.8911976,
      "lng": -0.5760307
    },
    {
      "centre_id": "grantown_on_spey",
      "centre_name": "Grantown-On-Spey",
      "lat": 57.3295089,
      "lng": -3.6104018
    },
    {
      "centre_id": "greenford_horsenden_lane",
      "centre_name": "Greenford Horsenden Lane",
      "lat": 51.5488071,
      "lng": -0.3309988
    },
    {
      "centre_id": "greenock",
      "centre_name": "Greenock",
      "lat": 55.9473423,
      "lng": -4.7564721
    },
    {
      "centre_id": "grimsby_coldwater",
      "centre_name": "Grimsby Coldwater",
      "lat": 53.5806208,
      "lng": -0.1135832
    },
    {
      "centre_id": "guildford",
      "centre_name": "Guildford",
      "lat": 51.2356068,
      "lng": -0.5732063
    },
    {
      "centre_id": "haddington",
      "centre_name": "Haddington",
      "lat": 55.9608288,
      "lng": -2.7820611
    },
    {
      "centre_id": "halifax",
      "centre_name": "Halifax",
      "lat": 53.7241949,
      "lng": -1.8907001
    },
    {
      "centre_id": "hamilton",
      "centre_name": "Hamilton",
      "lat": 57.6959,
      "lng": -4.2557
    },
    {
      "centre_id": "hartlepool",
      "centre_name": "Hartlepool",
      "lat": 54.6683573,
      "lng": -1.2128198
    },
    {
      "centre_id": "hastings_ore",
      "centre_name": "Hastings Ore",
      "lat": 50.8791476,
      "lng": 0.6151486
    },
    {
      "centre_id": "hawick",
      "centre_name": "Hawick",
      "lat": 55.422564,
      "lng": -2.7866951
    },
    {
      "centre_id": "heckmondwike",
      "centre_name": "Heckmondwike",
      "lat": 53.7074371,
      "lng": -1.6754499
    },
    {
      "centre_id": "hendon_london",
      "centre_name": "Hendon London",
      "lat": 51.5824581,
      "lng": -0.2289046
    },
    {
      "centre_id": "hereford",
      "centre_name": "Hereford",
      "lat": 52.0727799,
      "lng": -2.7131125
    },
    {
      "centre_id": "herne_bay",
      "centre_name": "Herne Bay",
      "lat": 51.3673845,
      "lng": 1.1437393
    },
    {
      "centre_id": "hexham",
      "centre_name": "Hexham",
      "lat": 54.971478,
      "lng": -2.1017927
    },
    {
      "centre_id": "heysham",
      "centre_name": "Heysham",
      "lat": 54.0494955,
      "lng": -2.890311
    },
    {
      "centre_id": "high_wycombe",
      "centre_name": "High Wycombe",
      "lat": 51.6317449,
      "lng": -0.75596
    },
    {
      "centre_id": "hinckley",
      "centre_name": "Hinckley",
      "lat": 52.5411172,
      "lng": -1.373688
    },
    {
      "centre_id": "hither_green_london",
      "centre_name": "Hither Green London",
      "lat": 51.4616864,
      "lng": -0.010742
    },
    {
      "centre_id": "hornchurch_london",
      "centre_name": "Hornchurch London",
      "lat": 51.5212372,
      "lng": 0.1824409
    },
    {
      "centre_id": "horsforth",
      "centre_name": "Horsforth",
      "lat": 53.8397978,
      "lng": -1.651467
    },
    {
      "centre_id": "huddersfield",
      "centre_name": "Huddersfield",
      "lat": 53.6468568,
      "lng": -1.7961112
    },
    {
      "centre_id": "hull",
      "centre_name": "Hull",
      "lat": 53.7435722,
      "lng": -0.3394758
    },
    {
      "centre_id": "huntly",
      "centre_name": "Huntly",
      "lat": 57.4474806,
      "lng": -2.7864246
    },
    {
      "centre_id": "hyde_manchester",
      "centre_name": "Hyde Manchester",
      "lat": 53.4476066,
      "lng": -2.1072663
    },
    {
      "centre_id": "inveraray",
      "centre_name": "Inveraray",
      "lat": 56.2303491,
      "lng": -5.0730947
    },
    {
      "centre_id": "ipswich",
      "centre_name": "Ipswich",
      "lat": 51.87249038,
      "lng": 0.928845203
    },
    {
      "centre_id": "islay_island",
      "centre_name": "Islay Island",
      "lat": 55.7585802,
      "lng": -6.1656723
    },
    {
      "centre_id": "isle_of_mull",
      "centre_name": "Isle of Mull",
      "lat": 56.4596987,
      "lng": -5.8620604
    },
    {
      "centre_id": "isle_of_skye_broadford",
      "centre_name": "Isle of Skye Broadford",
      "lat": 57.242713,
      "lng": -5.9139115
    },
    {
      "centre_id": "isle_of_tiree",
      "centre_name": "Isle of Tiree",
      "lat": 56.4539327,
      "lng": -6.9396039
    },
    {
      "centre_id": "isles_of_scilly",
      "centre_name": "Isles of Scilly",
      "lat": 49.9202695,
      "lng": -6.2902244
    },
    {
      "centre_id": "isleworth_fleming_way",
      "centre_name": "Isleworth Fleming Way",
      "lat": null,
      "lng": null
    },
    {
      "centre_id": "kendal_oxenholme_road",
      "centre_name": "Kendal Oxenholme Road",
      "lat": 54.3110638,
      "lng": -2.7353996
    },
    {
      "centre_id": "kettering",
      "centre_name": "Kettering",
      "lat": 52.3779276,
      "lng": -0.725218
    },
    {
      "centre_id": "kings_lynn",
      "centre_name": "Kings Lynn",
      "lat": 52.7538673,
      "lng": 0.3954774
    },
    {
      "centre_id": "kingussie",
      "centre_name": "Kingussie",
      "lat": 57.0802761,
      "lng": -4.051164
    },
    {
      "centre_id": "kirkcaldy",
      "centre_name": "Kirkcaldy",
      "lat": 56.1383644,
      "lng": -3.1252672
    },
    {
      "centre_id": "kyle_of_lochalsh",
      "centre_name": "Kyle of Lochalsh",
      "lat": 57.2808664,
      "lng": -5.7161192
    },
    {
      "centre_id": "lairg",
      "centre_name": "Lairg",
      "lat": 58.0018896,
      "lng": -4.3998683
    },
    {
      "centre_id": "lanark",
      "centre_name": "Lanark",
      "lat": 55.6736271,
      "lng": -3.7780361
    },
    {
      "centre_id": "launceston",
      "centre_name": "Launceston",
      "lat": 50.614451,
      "lng": -4.336351
    },
    {
      "centre_id": "leeds",
      "centre_name": "Leeds",
      "lat": 51.87249038,
      "lng": 0.928845203
    },
    {
      "centre_id": "leicester_cannock_street",
      "centre_name": "Leicester Cannock Street",
      "lat": 51.87249038,
      "lng": 0.928845203
    },
    {
      "centre_id": "leicester_wigston",
      "centre_name": "Leicester Wigston",
      "lat": 52.5857846,
      "lng": -1.1059373
    },
    {
      "centre_id": "leighton_buzzard_stanbridge_road",
      "centre_name": "Leighton Buzzard Stanbridge Road",
      "lat": 51.9117486,
      "lng": -0.630862
    },
    {
      "centre_id": "letchworth",
      "centre_name": "Letchworth",
      "lat": 51.9787147,
      "lng": -0.215228
    },
    {
      "centre_id": "lichfield",
      "centre_name": "Lichfield",
      "lat": 52.7048115,
      "lng": -1.7784168
    },
    {
      "centre_id": "lincoln",
      "centre_name": "Lincoln",
      "lat": 53.2466879,
      "lng": -0.5146945
    },
    {
      "centre_id": "llanelli",
      "centre_name": "Llanelli",
      "lat": 51.6860809,
      "lng": -4.1550921
    },
    {
      "centre_id": "lochgilphead",
      "centre_name": "Lochgilphead",
      "lat": 56.0260886,
      "lng": -5.4268275
    },
    {
      "centre_id": "loughborough",
      "centre_name": "Loughborough",
      "lat": 52.7808821,
      "lng": -1.2010251
    },
    {
      "centre_id": "loughton_london",
      "centre_name": "Loughton London",
      "lat": 51.4668087,
      "lng": 0.1468586
    },
    {
      "centre_id": "louth",
      "centre_name": "Louth",
      "lat": 53.3675163,
      "lng": -0.0022381
    },
    {
      "centre_id": "lowestoft_mobbs_way",
      "centre_name": "Lowestoft Mobbs Way",
      "lat": 52.4866052,
      "lng": 1.7177057
    },
    {
      "centre_id": "ludlow",
      "centre_name": "Ludlow",
      "lat": 52.3663184,
      "lng": -2.7105605
    },
    {
      "centre_id": "luton",
      "centre_name": "Luton",
      "lat": 51.8832748,
      "lng": -0.3798178
    },
    {
      "centre_id": "macclesfield",
      "centre_name": "Macclesfield",
      "lat": 53.2606635,
      "lng": -2.1255158
    },
    {
      "centre_id": "maidstone",
      "centre_name": "Maidstone",
      "lat": 51.2748258,
      "lng": 0.5231646
    },
    {
      "centre_id": "mallaig",
      "centre_name": "Mallaig",
      "lat": 57.0055177,
      "lng": -5.8286985
    },
    {
      "centre_id": "malton",
      "centre_name": "Malton",
      "lat": 54.1392092,
      "lng": -0.799531
    },
    {
      "centre_id": "melton_mowbray",
      "centre_name": "Melton Mowbray",
      "lat": 52.7644561,
      "lng": -0.8865674
    },
    {
      "centre_id": "merthyr_tydfil",
      "centre_name": "Merthyr Tydfil",
      "lat": 51.7455659,
      "lng": -3.3786082
    },
    {
      "centre_id": "middlesbrough",
      "centre_name": "Middlesbrough",
      "lat": 54.5547923,
      "lng": -1.1850719
    },
    {
      "centre_id": "mill_hill_london",
      "centre_name": "Mill Hill London",
      "lat": 51.6100418,
      "lng": -0.2440858
    },
    {
      "centre_id": "mitcham_london",
      "centre_name": "Mitcham London",
      "lat": 51.4055061,
      "lng": -0.1646016
    },
    {
      "centre_id": "monmouth",
      "centre_name": "Monmouth",
      "lat": 51.8064491,
      "lng": -2.7275874
    },
    {
      "centre_id": "montrose",
      "centre_name": "Montrose",
      "lat": 56.7114295,
      "lng": -2.4681544
    },
    {
      "centre_id": "morden_london",
      "centre_name": "Morden London",
      "lat": 51.3969239,
      "lng": -0.1993417
    },
    {
      "centre_id": "nelson",
      "centre_name": "Nelson",
      "lat": 53.8363428,
      "lng": -2.2116469
    },
    {
      "centre_id": "newbury_hambridge_lane",
      "centre_name": "Newbury Hambridge Lane",
      "lat": null,
      "lng": null
    },
    {
      "centre_id": "newport_gwent",
      "centre_name": "Newport Gwent",
      "lat": 51.5765402,
      "lng": -2.9439567
    },
    {
      "centre_id": "newton_abbot",
      "centre_name": "Newton Abbot",
      "lat": 50.5296441,
      "lng": -3.6112097
    },
    {
      "centre_id": "newton_stewart",
      "centre_name": "Newton Stewart",
      "lat": 54.9591514,
      "lng": -4.4706829
    },
    {
      "centre_id": "newtown",
      "centre_name": "Newtown",
      "lat": 52.5135785,
      "lng": -3.314371
    },
    {
      "centre_id": "norris_green_liverpool",
      "centre_name": "Norris Green Liverpool",
      "lat": 53.4492317,
      "lng": -2.9132191
    },
    {
      "centre_id": "northallerton",
      "centre_name": "Northallerton",
      "lat": 54.331661,
      "lng": -1.4257695
    },
    {
      "centre_id": "northampton",
      "centre_name": "Northampton",
      "lat": 52.2353801,
      "lng": -0.9021168
    },
    {
      "centre_id": "northwich",
      "centre_name": "Northwich",
      "lat": 53.2602539,
      "lng": -2.5145104
    },
    {
      "centre_id": "norwich_jupiter_road",
      "centre_name": "Norwich Jupiter Road",
      "lat": 52.6598534,
      "lng": 1.2806124
    },
    {
      "centre_id": "norwich_peachman_way",
      "centre_name": "Norwich Peachman Way",
      "lat": 52.6348562,
      "lng": 1.3708829
    },
    {
      "centre_id": "nottingham_colwick",
      "centre_name": "Nottingham Colwick",
      "lat": 52.9504823,
      "lng": -1.1137361
    },
    {
      "centre_id": "nuneaton",
      "centre_name": "Nuneaton",
      "lat": 52.4976369,
      "lng": -1.4768705
    },
    {
      "centre_id": "oban",
      "centre_name": "Oban",
      "lat": 56.4120528,
      "lng": -5.4723289
    },
    {
      "centre_id": "oswestry",
      "centre_name": "Oswestry",
      "lat": 52.8603096,
      "lng": -3.0548201
    },
    {
      "centre_id": "oxford_cowley",
      "centre_name": "Oxford Cowley",
      "lat": 51.7409356,
      "lng": -1.2023936
    },
    {
      "centre_id": "paisley",
      "centre_name": "Paisley",
      "lat": 55.8455828,
      "lng": -4.4239646
    },
    {
      "centre_id": "peebles",
      "centre_name": "Peebles",
      "lat": 55.6517553,
      "lng": -3.1885456
    },
    {
      "centre_id": "pembroke_dock",
      "centre_name": "Pembroke Dock",
      "lat": 51.693539,
      "lng": -4.9392016
    },
    {
      "centre_id": "perth_arran_road",
      "centre_name": "Perth Arran Road",
      "lat": 56.4162078,
      "lng": -3.4574009
    },
    {
      "centre_id": "peterborough",
      "centre_name": "Peterborough",
      "lat": 52.5725769,
      "lng": -0.2427336
    },
    {
      "centre_id": "peterhead",
      "centre_name": "Peterhead",
      "lat": 57.4910589,
      "lng": -1.807068
    },
    {
      "centre_id": "pinner_london",
      "centre_name": "Pinner London",
      "lat": 51.5947555,
      "lng": -0.3829509
    },
    {
      "centre_id": "pitlochry",
      "centre_name": "Pitlochry",
      "lat": 56.701969,
      "lng": -3.7306846
    },
    {
      "centre_id": "plymouth",
      "centre_name": "Plymouth",
      "lat": 50.4095962,
      "lng": -4.1623038
    },
    {
      "centre_id": "pontefract",
      "centre_name": "Pontefract",
      "lat": 53.6917422,
      "lng": -1.3105722
    },
    {
      "centre_id": "poole",
      "centre_name": "Poole",
      "lat": 50.7179472,
      "lng": -1.981521
    },
    {
      "centre_id": "portsmouth",
      "centre_name": "Portsmouth",
      "lat": 50.857085,
      "lng": -1.1097044
    },
    {
      "centre_id": "preston",
      "centre_name": "Preston",
      "lat": 53.7597518,
      "lng": -2.7591557
    },
    {
      "centre_id": "pwllheli",
      "centre_name": "Pwllheli",
      "lat": 52.8808724,
      "lng": -4.4233345
    },
    {
      "centre_id": "reading",
      "centre_name": "Reading",
      "lat": 51.4382718,
      "lng": -0.9652685
    },
    {
      "centre_id": "redditch",
      "centre_name": "Redditch",
      "lat": 52.2785895,
      "lng": -1.9361227
    },
    {
      "centre_id": "rhyl",
      "centre_name": "Rhyl",
      "lat": 53.3207425,
      "lng": -3.4907258
    },
    {
      "centre_id": "rochdale_manchester",
      "centre_name": "Rochdale Manchester",
      "lat": 53.5960849,
      "lng": -2.1360447
    },
    {
      "centre_id": "rotherham",
      "centre_name": "Rotherham",
      "lat": 53.4310417,
      "lng": -1.355187
    },
    {
      "centre_id": "rothesay",
      "centre_name": "Rothesay",
      "lat": 55.8375224,
      "lng": -5.0535072
    },
    {
      "centre_id": "rugby",
      "centre_name": "Rugby",
      "lat": 52.3726682,
      "lng": -1.2620038
    },
    {
      "centre_id": "sale_manchester",
      "centre_name": "Sale Manchester",
      "lat": 53.4497719,
      "lng": -2.3458172
    },
    {
      "centre_id": "salisbury",
      "centre_name": "Salisbury",
      "lat": 51.0690613,
      "lng": -1.7954134
    },
    {
      "centre_id": "scarborough",
      "centre_name": "Scarborough",
      "lat": 54.2820009,
      "lng": -0.4011868
    },
    {
      "centre_id": "scunthorpe",
      "centre_name": "Scunthorpe",
      "lat": 53.5922343,
      "lng": -0.6450699
    },
    {
      "centre_id": "sevenoaks",
      "centre_name": "Sevenoaks",
      "lat": 51.2745218,
      "lng": 0.1961166
    },
    {
      "centre_id": "sheffield_handsworth",
      "centre_name": "Sheffield Handsworth",
      "lat": 53.3769296,
      "lng": -1.3953488
    },
    {
      "centre_id": "sheffield_middlewood_road",
      "centre_name": "Sheffield Middlewood Road",
      "lat": 53.420671,
      "lng": -1.5001206
    },
    {
      "centre_id": "shrewsbury",
      "centre_name": "Shrewsbury",
      "lat": 52.707755,
      "lng": -2.7540658
    },
    {
      "centre_id": "sidcup_london",
      "centre_name": "Sidcup London",
      "lat": 51.4259765,
      "lng": 0.1042684
    },
    {
      "centre_id": "skegness",
      "centre_name": "Skegness",
      "lat": 53.1437506,
      "lng": 0.3428958
    },
    {
      "centre_id": "skipton",
      "centre_name": "Skipton",
      "lat": 53.9618497,
      "lng": -2.0160287
    },
    {
      "centre_id": "slough_london",
      "centre_name": "Slough London",
      "lat": 51.5227054,
      "lng": -0.6213452
    },
    {
      "centre_id": "south_shields",
      "centre_name": "South Shields",
      "lat": 54.9987414,
      "lng": -1.4321848
    },
    {
      "centre_id": "southall_london",
      "centre_name": "Southall London",
      "lat": 51.5108299,
      "lng": -0.3713515
    },
    {
      "centre_id": "southampton_forest_hills",
      "centre_name": "Southampton Forest Hills",
      "lat": 50.9336972,
      "lng": -1.3640415
    },
    {
      "centre_id": "southampton_maybush",
      "centre_name": "Southampton Maybush",
      "lat": 50.9336859,
      "lng": -1.4528577
    },
    {
      "centre_id": "southend_on_sea",
      "centre_name": "Southend-On-Sea",
      "lat": 51.5388241,
      "lng": 0.7128137
    },
    {
      "centre_id": "southport_liverpool",
      "centre_name": "Southport Liverpool",
      "lat": 53.6452931,
      "lng": -3.0098635
    },
    {
      "centre_id": "speke_liverpool",
      "centre_name": "Speke Liverpool",
      "lat": 53.3580861,
      "lng": -2.8668656
    },
    {
      "centre_id": "st_albans",
      "centre_name": "St Albans",
      "lat": 51.753051,
      "lng": -0.3379675
    },
    {
      "centre_id": "st_helens_liverpool",
      "centre_name": "St Helens Liverpool",
      "lat": 53.4537825,
      "lng": -2.7391233
    },
    {
      "centre_id": "stafford",
      "centre_name": "Stafford",
      "lat": 52.8063157,
      "lng": -2.1163818
    },
    {
      "centre_id": "steeton",
      "centre_name": "Steeton",
      "lat": 53.896673,
      "lng": -1.9494405
    },
    {
      "centre_id": "stevenage",
      "centre_name": "Stevenage",
      "lat": 51.9016663,
      "lng": -0.2027155
    },
    {
      "centre_id": "stirling",
      "centre_name": "Stirling",
      "lat": 56.1181242,
      "lng": -3.9360012
    },
    {
      "centre_id": "stoke_on_trent_cobridge",
      "centre_name": "Stoke-On-Trent Cobridge",
      "lat": null,
      "lng": null
    },
    {
      "centre_id": "stoke_on_trent_newcastle_under_lyme",
      "centre_name": "Stoke-on-Trent Newcastle-Under-Lyme",
      "lat": 53.0205639,
      "lng": -2.229993
    },
    {
      "centre_id": "stranraer",
      "centre_name": "Stranraer",
      "lat": 54.9044617,
      "lng": -5.0264588
    },
    {
      "centre_id": "sunderland",
      "centre_name": "Sunderland",
      "lat": 54.9058512,
      "lng": -1.3828727
    },
    {
      "centre_id": "swansea",
      "centre_name": "Swansea",
      "lat": 51.6195955,
      "lng": -3.9459248
    },
    {
      "centre_id": "swindon",
      "centre_name": "Swindon",
      "lat": 51.5615327,
      "lng": -1.7854322
    },
    {
      "centre_id": "taunton",
      "centre_name": "Taunton",
      "lat": 51.0147895,
      "lng": -3.1029086
    },
    {
      "centre_id": "telford",
      "centre_name": "Telford",
      "lat": 52.6780532,
      "lng": -2.4514219
    },
    {
      "centre_id": "thurso",
      "centre_name": "Thurso",
      "lat": 58.5950797,
      "lng": -3.5197482
    },
    {
      "centre_id": "tilbury",
      "centre_name": "Tilbury",
      "lat": 51.4616124,
      "lng": 0.3636802
    },
    {
      "centre_id": "tolworth_london",
      "centre_name": "Tolworth London",
      "lat": 51.3758498,
      "lng": -0.2787071
    },
    {
      "centre_id": "trowbridge",
      "centre_name": "Trowbridge",
      "lat": 51.3161569,
      "lng": -2.2024324
    },
    {
      "centre_id": "tunbridge_wells",
      "centre_name": "Tunbridge Wells",
      "lat": 51.1371483,
      "lng": 0.2673446
    },
    {
      "centre_id": "ullapool",
      "centre_name": "Ullapool",
      "lat": 57.8956683,
      "lng": -5.1599177
    },
    {
      "centre_id": "upton",
      "centre_name": "Upton",
      "lat": 52.5907194,
      "lng": -0.3672758
    },
    {
      "centre_id": "uxbridge_london",
      "centre_name": "Uxbridge London",
      "lat": 51.5465563,
      "lng": -0.4817451
    },
    {
      "centre_id": "wakefield",
      "centre_name": "Wakefield",
      "lat": 53.6829541,
      "lng": -1.4967286
    },
    {
      "centre_id": "wallasey",
      "centre_name": "Wallasey",
      "lat": 53.4241208,
      "lng": -3.0394101
    },
    {
      "centre_id": "wanstead_london",
      "centre_name": "Wanstead London",
      "lat": 51.5756739,
      "lng": 0.0277989
    },
    {
      "centre_id": "warwick_wedgenock_house",
      "centre_name": "Warwick Wedgenock House",
      "lat": null,
      "lng": null
    },
    {
      "centre_id": "watford",
      "centre_name": "Watford",
      "lat": 51.6553875,
      "lng": -0.3957425
    },
    {
      "centre_id": "wednesbury",
      "centre_name": "Wednesbury",
      "lat": 52.5521806,
      "lng": -2.0224441
    },
    {
      "centre_id": "wellingborough",
      "centre_name": "Wellingborough",
      "lat": 52.30189,
      "lng": -0.6937309
    },
    {
      "centre_id": "west_didsbury_manchester",
      "centre_name": "West Didsbury Manchester",
      "lat": 53.4244499,
      "lng": -2.2361281
    },
    {
      "centre_id": "west_wickham_london",
      "centre_name": "West Wickham London",
      "lat": 51.3764356,
      "lng": -0.0178222
    },
    {
      "centre_id": "weston_super_mare",
      "centre_name": "Weston-super-Mare",
      "lat": 51.3471927,
      "lng": -2.9778916
    },
    {
      "centre_id": "whitby",
      "centre_name": "Whitby",
      "lat": 54.4874141,
      "lng": -0.6155111
    },
    {
      "centre_id": "wick",
      "centre_name": "Wick",
      "lat": 58.4424965,
      "lng": -3.0908026
    },
    {
      "centre_id": "widnes",
      "centre_name": "Widnes",
      "lat": 53.3646888,
      "lng": -2.7283328
    },
    {
      "centre_id": "winchester",
      "centre_name": "Winchester",
      "lat": 51.0612766,
      "lng": -1.3131692
    },
    {
      "centre_id": "wolverhampton",
      "centre_name": "Wolverhampton",
      "lat": 52.5847651,
      "lng": -2.127567
    },
    {
      "centre_id": "wood_green_london",
      "centre_name": "Wood Green London",
      "lat": 51.5900486,
      "lng": -0.1443935
    },
    {
      "centre_id": "worcester",
      "centre_name": "Worcester",
      "lat": 51.87249038,
      "lng": 0.928845203
    },
    {
      "centre_id": "workington",
      "centre_name": "Workington",
      "lat": 54.64338,
      "lng": -3.5453529
    },
    {
      "centre_id": "worksop",
      "centre_name": "Worksop",
      "lat": 53.3042362,
      "lng": -1.1246168
    },
    {
      "centre_id": "yeovil",
      "centre_name": "Yeovil",
      "lat": 50.9420451,
      "lng": -2.6318629
    },
    {
      "centre_id": "york",
      "centre_name": "York",
      "lat": 53.9888343,
      "lng": -1.0488985
    }
  ]
}
